{
  "name": "timeline",
  "type": "component",
  "description": "A beautiful timeline component with scroll-based animations",
  "files": [
    {
      "name": "timeline-base.tsx",
      "path": "component-library/components/ui/timeline/timeline-base.tsx"
    },
    {
      "name": "timeline-standard.tsx", 
      "path": "component-library/components/ui/timeline/timeline-standard.tsx"
    },
    {
      "name": "timeline.types.ts",
      "path": "component-library/components/ui/timeline/timeline.types.ts"
    },
    {
      "name": "index.tsx",
      "path": "component-library/components/ui/timeline/index.tsx"
    }
  ],
  "dependencies": ["framer-motion", "@tabler/icons-react"],
  "devDependencies": [],
  "tailwind": {
    "config": {}
  },
  "cssVars": {},
  "meta": {
    "features": [
      "Scroll-based animations",
      "Sticky headers",
      "Responsive design", 
      "Dark mode support"
    ],
    "category": "display",
    "variants": 1
  }
}